README.txt
setup.py
docs/HISTORY.txt
docs/INSTALL.txt
docs/LICENSE.GPL
docs/LICENSE.txt
plonetheme/__init__.py
plonetheme.netsightintranet.egg-info/PKG-INFO
plonetheme.netsightintranet.egg-info/SOURCES.txt
plonetheme.netsightintranet.egg-info/dependency_links.txt
plonetheme.netsightintranet.egg-info/entry_points.txt
plonetheme.netsightintranet.egg-info/namespace_packages.txt
plonetheme.netsightintranet.egg-info/not-zip-safe
plonetheme.netsightintranet.egg-info/paster_plugins.txt
plonetheme.netsightintranet.egg-info/requires.txt
plonetheme.netsightintranet.egg-info/top_level.txt
plonetheme/netsightintranet/__init__.py
plonetheme/netsightintranet/configure.zcml
plonetheme/netsightintranet/profiles.zcml
plonetheme/netsightintranet/setuphandlers.py
plonetheme/netsightintranet/skins.zcml
plonetheme/netsightintranet/version.txt
plonetheme/netsightintranet/browser/__init__.py
plonetheme/netsightintranet/browser/browser.py
plonetheme/netsightintranet/browser/configure.zcml
plonetheme/netsightintranet/browser/folderfactories.py
plonetheme/netsightintranet/browser/interfaces.py
plonetheme/netsightintranet/browser/lightboxing.py
plonetheme/netsightintranet/browser/menu.py
plonetheme/netsightintranet/browser/portlets.py
plonetheme/netsightintranet/browser/viewlets.py
plonetheme/netsightintranet/browser/images/closebox.png
plonetheme/netsightintranet/browser/js/lightboxing-plugins.js
plonetheme/netsightintranet/browser/kss/edit_mode.kss
plonetheme/netsightintranet/browser/kss/lightboxing.kss
plonetheme/netsightintranet/browser/stylesheets/deplone3.css
plonetheme/netsightintranet/browser/stylesheets/lightbox.css
plonetheme/netsightintranet/browser/stylesheets/main.css
plonetheme/netsightintranet/browser/stylesheets/netsightintranet_IEFixes.css
plonetheme/netsightintranet/browser/templates/contentactions.pt
plonetheme/netsightintranet/browser/templates/contentmenu.pt
plonetheme/netsightintranet/browser/templates/contentviews.pt
plonetheme/netsightintranet/browser/templates/delete_confirmation.pt
plonetheme/netsightintranet/browser/templates/document_byline.pt
plonetheme/netsightintranet/browser/templates/edit_toolbar.pt
plonetheme/netsightintranet/browser/templates/folder_factories.pt
plonetheme/netsightintranet/browser/templates/intranet_document_view.pt
plonetheme/netsightintranet/browser/templates/macropage.pt
plonetheme/netsightintranet/browser/templates/navigation.pt
plonetheme/netsightintranet/browser/templates/navigation_recurse.pt
