Metadata-Version: 1.0
Name: plonetheme.netsightintranet
Version: 1.2
Summary: A clean, intranet theme for Plone 3.0
Home-page: http://plone.org/products/plonetheme.netsightintranet
Author: Matthew Sital-Singh, Netsight Internet Solutions
Author-email: mattss@netsight.co.uk
License: GPL
Keywords: web zope plone theme intranet
Platform: UNKNOWN
Classifier: Framework :: Plone
Classifier: Programming Language :: Python
